pyn8n/.env
pyn8n/__init__.py
pyn8n/api.py
pyn8n/cli.py
pyn8n/cmds/__init__.py
pyn8n/cmds/devops.py
pyn8n/create_creds.py
pyn8n/create_factorial_workflow.py
pyn8n/create_workflow.py
pyn8n/exceptions.py
pyn8n/factorial_workflow.json
pyn8n/models.py
pyn8n/n8n_client.py
pyn8n/n8n_decorator.py
pyn8n/n8n_nodes.py
pyn8n-2024.12.24.4.dist-info/METADATA
pyn8n-2024.12.24.4.dist-info/WHEEL
pyn8n-2024.12.24.4.dist-info/entry_points.txt
pyn8n-2024.12.24.4.dist-info/RECORD
