Metadata-Version: 2.1
Name: pyn8n
Version: 2024.12.24.4
Summary: N8N client and AI tools.
Home-page: https://github.com/user/seanchatmangpt/pyn8n
Author: Sean Chatman
Author-email: info@chatmangpt.com
Requires-Python: >=3.12,<4.0
Classifier: Programming Language :: Python :: 3
Classifier: Programming Language :: Python :: 3.12
Classifier: Programming Language :: Python :: 3.13
Requires-Dist: aio-apiclient (>=1.7.0,<2.0.0)
Requires-Dist: aiofiles (>=24.1.0,<25.0.0)
Requires-Dist: api-client-pydantic (>=3.1.0,<4.0.0)
Requires-Dist: cloudpickle (>=3.1.0,<4.0.0)
Requires-Dist: coloredlogs (>=15.0.1)
Requires-Dist: dslmodel (>=2024.12.22.2,<2025.0.0.0)
Requires-Dist: dspy-ai (>=2.5.43,<3.0.0)
Requires-Dist: fastapi[all] (>=0.110.1)
Requires-Dist: gunicorn (>=21.2.0)
Requires-Dist: pydantic (>=2.10.4,<3.0.0)
Requires-Dist: pydantic-ai[logfire] (>=0.0.14,<0.0.15)
Requires-Dist: respx (>=0.22.0,<0.23.0)
Requires-Dist: typer[all] (>=0.12.0)
Requires-Dist: uvicorn[standard] (>=0.29.0)
Project-URL: Repository, https://github.com/user/seanchatmangpt/pyn8n
